Metadata-Version: 1.1
Name: digimat.units
Version: 0.0.1
Summary: Digimat Units
Home-page: http://www.digimat.ch
Author: Frederic Hess
Author-email: fhess@st-sa.ch
License: PSF
Platform: UNKNOWN
Classifier: Development Status :: 4 - Beta
Classifier: Programming Language :: Python :: 3
